pathlib3x/__init__.py
pathlib3x/__init__conf__.py
pathlib3x/_typeshed.pyi
pathlib3x/pathlib3x.py
pathlib3x/pathlib3x.pyi
pathlib3x/pathlib3x_cli.py
pathlib3x/py.typed
pathlib3x/typing_extensions.pyi
pathlib3x-2.0.3.dist-info/LICENSE
pathlib3x-2.0.3.dist-info/METADATA
pathlib3x-2.0.3.dist-info/WHEEL
pathlib3x-2.0.3.dist-info/entry_points.txt
pathlib3x-2.0.3.dist-info/top_level.txt
pathlib3x-2.0.3.dist-info/RECORD
